rsa/__init__.py
rsa/core/RSA.py
rsa/core/cli.py
rsa/main.py
rsa/utils/GenPrimeNumber.py
rsa/utils/JBR.py
rsa/utils/MDC.py
rsa/utils/MillerRabin.py
rsa/utils/__init__.py
rsa/utils/cli/read_files.py
rsa/utils/cli/validate_arguments.py
rsa/utils/cli/write_files.py
rsa/utils/decode_rsa_key.py
rsa/utils/der/DataTypes/PrivateKey.py
rsa/utils/der/DataTypes/PublicKey.py
rsa/utils/logging/config.py
rsa_cli-0.3.1.dist-info/LICENSE
rsa_cli-0.3.1.dist-info/METADATA
rsa_cli-0.3.1.dist-info/WHEEL
rsa_cli-0.3.1.dist-info/entry_points.txt
rsa_cli-0.3.1.dist-info/RECORD
