Metadata-Version: 2.1
Name: rsa-cli
Version: 0.3.1
Summary: RSA-CLI é uma ferramenta de linha de comando utilizada para criar chaves RSA públicas e privadas, realizar a cifração e decifração de informações
License: MIT
Author: Pedro Bueno
Author-email: contato0113@gmail.com
Requires-Python: >=3.9,<4.0
Classifier: Development Status :: 5 - Production/Stable
Classifier: Environment :: Console
Classifier: License :: OSI Approved :: MIT License
Classifier: Natural Language :: Portuguese (Brazilian)
Classifier: Programming Language :: Python :: 3
Classifier: Programming Language :: Python :: 3.9
Classifier: Programming Language :: Python :: 3.10
Classifier: Programming Language :: Python :: 3.11
Classifier: Programming Language :: Python :: 3.12
Classifier: Topic :: Education
Requires-Dist: pyasn1 (>=0.6.0,<0.7.0)
Requires-Dist: pytest (>=8.2.2,<9.0.0)
Requires-Dist: rich (>=13.7.1,<14.0.0)
Requires-Dist: typer (>=0.12.3,<0.13.0)
Project-URL: Código, https://github.com/PHBueno/RSA
Project-URL: Documentação, https://rsa-cli.readthedocs.io/pt-br/latest/
